[
  {
    "id": "hashed_id_1",
    "name": "John Doe",
    "email": "masked_email_1@example.com",
    "age": 32,
    "gender": "Male",
    "city": "New York",
    "country": "USA",
    "salary": 55000,
    "education": "Bachelor's Degree",
    "employment_status": "Employed",
    "department": "Sales",
    "hobby": "Reading",
    "marital_status": "Married",
    "children": 2,
    "years_of_experience": 5,
    "performance_rating": 4.5,
    "last_promotion_date": "2023-05-12",
    "manager": "Jane Smith",
    "work_location": "Office",
    "work_from_home_days": 2,
    "start_date": "2018-07-15",
    "team_size": 10,
    "working_hours_per_day": 8
  },
  {
    "id": "hashed_id_2",
    "name": "Jane Smith",
    "email": "masked_email_2@example.com",
    "age": 28,
    "gender": "Female",
    "city": "Los Angeles",
    "country": "USA",
    "salary": 60000,
    "education": "Master's Degree",
    "employment_status": "Employed",
    "department": "Marketing",
    "hobby": "Photography",
    "marital_status": "Single",
    "children": 0,
    "years_of_experience": 7,
    "performance_rating": 4.7,
    "last_promotion_date": "2022-11-20",
    "manager": "David Johnson",
    "work_location": "Remote",
    "work_from_home_days": 4,
    "start_date": "2016-09-20",
    "team_size": 8,
    "working_hours_per_day": 7
  },
  {
    "id": "hashed_id_3",
    "name": "Michael Brown",
    "email": "masked_email_3@example.com",
    "age": 35,
    "gender": "Male",
    "city": "Chicago",
    "country": "USA",
    "salary": 70000,
    "education": "PhD",
    "employment_status": "Employed",
    "department": "Research & Development",
    "hobby": "Playing Guitar",
    "marital_status": "Married",
    "children": 1,
    "years_of_experience": 10,
    "performance_rating": 4.9,
    "last_promotion_date": "2021-03-10",
    "manager": "Emily Wilson",
    "work_location": "Office",
    "work_from_home_days": 1,
    "start_date": "2011-08-10",
    "team_size": 15,
    "working_hours_per_day": 8
  }
]

